pymyair/__init__.py
pymyair/cli.py
pymyair/pymyair.py
pymyair-0.2.1.dist-info/AUTHORS.rst
pymyair-0.2.1.dist-info/LICENSE
pymyair-0.2.1.dist-info/METADATA
pymyair-0.2.1.dist-info/WHEEL
pymyair-0.2.1.dist-info/entry_points.txt
pymyair-0.2.1.dist-info/top_level.txt
pymyair-0.2.1.dist-info/RECORD
