Metadata-Version: 2.1
Name: pymyair
Version: 0.2.1
Summary: A simple Python API that wraps the HTTP based API exposed by the MyPlace service that runs on Advantage Air supplied Android tablets.
Home-page: https://github.com/smallsam/pymyair
Author: Sam Richards
Author-email: me@smallsam.com
License: MIT license
Keywords: pymyair
Platform: UNKNOWN
Classifier: Development Status :: 4 - Beta
Classifier: Intended Audience :: Developers
Classifier: License :: OSI Approved :: MIT License
Classifier: Natural Language :: English
Classifier: Programming Language :: Python :: 2
Classifier: Programming Language :: Python :: 2.6
Classifier: Programming Language :: Python :: 2.7
Classifier: Programming Language :: Python :: 3
Classifier: Programming Language :: Python :: 3.3
Classifier: Programming Language :: Python :: 3.4
Classifier: Programming Language :: Python :: 3.5
Requires-Dist: Click (>=6.0)
Requires-Dist: requests (>=2)
